phy_rx/generador_de_relojes.v
module generador_de_relojes( 
    input wire CLK32,
    output wire CLK16, CLK8, CLK4, CLK2, CLK);

    wire EN1;
    wire EN2;
    wire EN3;
    wire EN4;

    and and0(EN1, CLK16, 1'b1);
    and and0(EN2, CLK8, EN1);
    and and0(EN3, CLK4, EN2);
    and and0(EN4, CLK2, EN3);

    flipflop_t ff0(.T(1'b1), .CLK(CLK32), .Q(CLK16));
    flipflop_t ff1(.T(EN1), .CLK(CLK32), .Q(CLK8));
    flipflop_t ff2(.T(EN2), .CLK(CLK32), .Q(CLK4));
    flipflop_t ff3(.T(EN3), .CLK(CLK32), .Q(CLK2));
    flipflop_t ff4(.T(EN4), .CLK(CLK32), .Q(CLK));

endmodule

module flipflop_t(
    input wire T, CLK,
    output reg Q);
    
    initial begin    
    Q <= 1'b0;
    end
	always @(posedge CLK) begin
        if (T) begin
            Q <= ~Q;
        end  
        else begin
            Q <= Q;
        end 
    end
endmodule

phy_rx/phy_rx_tester.v
module phy_rx_tester(
    output reg serial_o0,
    output reg serial_o1,
    output reg clk32,
    output reg reset, 
    input wire [31:0] output_bus);
    
    
    always #1 clk32 <= ~clk32;

    // Condición inicial para todas las posibles pruebas.
    initial 
    begin    
    clk32 <= 0;
    serial_o0 <= 0;
    serial_o1 <= 0;
    reset <= 1;
    end

    // Aquí se mandan las señales estratégicamente para cumplir con la solución.
    initial begin
    $dumpfile("phy_rx.vcd");   
    $dumpvars;
    @(posedge clk32)
    reset <= 0 ;
    @(posedge clk32) serial_o0 <= 1; serial_o1 <= 1; 
    @(posedge clk32) serial_o0 <= 0; serial_o1 <= 0;  
    @(posedge clk32) serial_o0 <= 1; serial_o1 <= 1;
    @(posedge clk32) serial_o0 <= 1; serial_o1 <= 1; 
    @(posedge clk32) serial_o0 <= 1; serial_o1 <= 1;  
    @(posedge clk32) serial_o0 <= 1; serial_o1 <= 1;
    @(posedge clk32) serial_o0 <= 0; serial_o1 <= 0; 
    @(posedge clk32) serial_o0 <= 0; serial_o1 <= 0;

    @(posedge clk32) serial_o0 <= 1; serial_o1 <= 1; 
    @(posedge clk32) serial_o0 <= 0; serial_o1 <= 0;  
    @(posedge clk32) serial_o0 <= 1; serial_o1 <= 1;
    @(posedge clk32) serial_o0 <= 1; serial_o1 <= 1; 
    @(posedge clk32) serial_o0 <= 1; serial_o1 <= 1;  
    @(posedge clk32) serial_o0 <= 1; serial_o1 <= 1;
    @(posedge clk32) serial_o0 <= 0; serial_o1 <= 0; 
    @(posedge clk32) serial_o0 <= 0; serial_o1 <= 0;

    @(posedge clk32) serial_o0 <= 1; serial_o1 <= 1; 
    @(posedge clk32) serial_o0 <= 0; serial_o1 <= 0;  
    @(posedge clk32) serial_o0 <= 1; serial_o1 <= 1;
    @(posedge clk32) serial_o0 <= 1; serial_o1 <= 1; 
    @(posedge clk32) serial_o0 <= 1; serial_o1 <= 1;  
    @(posedge clk32) serial_o0 <= 1; serial_o1 <= 1;
    @(posedge clk32) serial_o0 <= 0; serial_o1 <= 0; 
    @(posedge clk32) serial_o0 <= 0; serial_o1 <= 0;

    @(posedge clk32) serial_o0 <= 1; serial_o1 <= 1; 
    @(posedge clk32) serial_o0 <= 0; serial_o1 <= 0;  
    @(posedge clk32) serial_o0 <= 1; serial_o1 <= 1;
    @(posedge clk32) serial_o0 <= 1; serial_o1 <= 1; 
    @(posedge clk32) serial_o0 <= 1; serial_o1 <= 1;  
    @(posedge clk32) serial_o0 <= 1; serial_o1 <= 1;
    @(posedge clk32) serial_o0 <= 0; serial_o1 <= 0; 
    @(posedge clk32) serial_o0 <= 0; serial_o1 <= 0;

    @(posedge clk32) serial_o0 <= 1; serial_o1 <= 1;  
    @(posedge clk32) serial_o0 <= 1; serial_o1 <= 1;
    @(posedge clk32) serial_o0 <= 1; serial_o1 <= 1; 
    @(posedge clk32) serial_o0 <= 1; serial_o1 <= 1;  
    @(posedge clk32) serial_o0 <= 1; serial_o1 <= 1;
    @(posedge clk32) serial_o0 <= 1; serial_o1 <= 1; 
    @(posedge clk32) serial_o0 <= 1; serial_o1 <= 1;  
    @(posedge clk32) serial_o0 <= 1; serial_o1 <= 1;

    @(posedge clk32) serial_o0 <= 1; serial_o1 <= 1; 
    @(posedge clk32) serial_o0 <= 1; serial_o1 <= 1;  
    @(posedge clk32) serial_o0 <= 1; serial_o1 <= 1;
    @(posedge clk32) serial_o0 <= 0; serial_o1 <= 0; 
    @(posedge clk32) serial_o0 <= 1; serial_o1 <= 1;  
    @(posedge clk32) serial_o0 <= 1; serial_o1 <= 1;
    @(posedge clk32) serial_o0 <= 1; serial_o1 <= 1; 
    @(posedge clk32) serial_o0 <= 0; serial_o1 <= 0;

    @(posedge clk32) serial_o0 <= 1; serial_o1 <= 1;  
    @(posedge clk32) serial_o0 <= 1; serial_o1 <= 1;
    @(posedge clk32) serial_o0 <= 1; serial_o1 <= 1; 
    @(posedge clk32) serial_o0 <= 1; serial_o1 <= 1;  
    @(posedge clk32) serial_o0 <= 1; serial_o1 <= 1;
    @(posedge clk32) serial_o0 <= 1; serial_o1 <= 1; 
    @(posedge clk32) serial_o0 <= 1; serial_o1 <= 1;  
    @(posedge clk32) serial_o0 <= 1; serial_o1 <= 1;

    @(posedge clk32) serial_o0 <= 1; serial_o1 <= 1; 
    @(posedge clk32) serial_o0 <= 1; serial_o1 <= 1;  
    @(posedge clk32) serial_o0 <= 1; serial_o1 <= 1;
    @(posedge clk32) serial_o0 <= 0; serial_o1 <= 0; 
    @(posedge clk32) serial_o0 <= 1; serial_o1 <= 1;  
    @(posedge clk32) serial_o0 <= 1; serial_o1 <= 1;
    @(posedge clk32) serial_o0 <= 1; serial_o1 <= 1; 
    @(posedge clk32) serial_o0 <= 0; serial_o1 <= 0;

    @(posedge clk32) serial_o0 <= 1; serial_o1 <= 1; 
    @(posedge clk32) serial_o0 <= 1; serial_o1 <= 1;  
    @(posedge clk32) serial_o0 <= 1; serial_o1 <= 1;
    @(posedge clk32) serial_o0 <= 0; serial_o1 <= 0; 
    @(posedge clk32) serial_o0 <= 1; serial_o1 <= 1;  
    @(posedge clk32) serial_o0 <= 1; serial_o1 <= 1;
    @(posedge clk32) serial_o0 <= 1; serial_o1 <= 1; 
    @(posedge clk32) serial_o0 <= 0; serial_o1 <= 0;
  
    @(posedge clk32) serial_o0 <= 1; serial_o1 <= 1; 
    @(posedge clk32) serial_o0 <= 0; serial_o1 <= 0;  
    @(posedge clk32) serial_o0 <= 1; serial_o1 <= 1;
    @(posedge clk32) serial_o0 <= 1; serial_o1 <= 1; 
    @(posedge clk32) serial_o0 <= 1; serial_o1 <= 1;  
    @(posedge clk32) serial_o0 <= 1; serial_o1 <= 1;
    @(posedge clk32) serial_o0 <= 0; serial_o1 <= 0; 
    @(posedge clk32) serial_o0 <= 0; serial_o1 <= 0;
    #100 $finish;    
    end
endmodule

phy_rx/un_striping.v
module un_striping
(
    input clk_2f,
	input [31:0] lane_0,
	input [31:0] lane_1,
	input valid_0,
    input valid_1,
	input reset,
	output reg [31:0] data_out,
    output reg  valid_out
);
reg selector;
always @(posedge clk_2f) 
begin
    if(reset == 1)
    begin
        selector <=0;
        valid_out <= 0;
        data_out <= 32'h00000000;
    end
    else 
    begin
        selector <= 0;
        //valid_out <= 0;
        if(valid_0 == 1 && selector == 0) 
        begin
            data_out <= lane_0 ;
            selector <= ~selector;
            valid_out <= 1;
        end

        else if(valid_1 == 1 && selector == 1) 
        begin
            data_out <= lane_1 ;
            selector <= ~selector;
            valid_out <= 1;
        end

        else if (valid_0 == 0 && selector == 0) 
        begin
            valid_out <= 0;
            selector <= ~selector; //continuar haciendo toogle aunque valid este en 0
            data_out <= 32'h00000000;
        end

        else if (valid_1 == 0 && selector == 1) 
        begin
            valid_out <= 0;
            selector <= ~selector; //continuar haciendo toogle aunque valid este en 0
            data_out <= 32'h00000000;
        end
    end
end
endmodule

phy_rx/ochoBit_32Bit.v
module ochoBit_32Bit ( input wire clk_4f,
                input wire clk_f,
                input wire [7:0] data_in,
                input wire valid_in,
                output reg valid_out,
                output reg [31:0] data_out   
);

reg [1:0]contador;  // contador para mantener 'track' de datos a transmitir

//initial begin
  //  contador = 0;  // Inicializar contador
//end

always @(posedge clk_4f)begin  

    if (valid_in == 1)begin  // si valid_in vale 1, se pasan los datos
      valid_out <= valid_in;  
      
     if(contador == 0)begin
        data_out[31:24] <= data_in [7:0];  // pasar data in de 8b a los 8b MSB de data_out
        contador = contador + 1; 
     end

     else if (contador == 1)begin
         data_out[23:16] <= data_in [7:0];  // pasar siguiente data in a siguientes 8b de data_out
         contador = contador + 1; 
     end

     else if (contador == 2)begin
         data_out[15:8] <= data_in [7:0];  // pasar siguiente data in a siguientes 8b de data_out
         contador = contador + 1; 
     end

     else if (contador == 3)begin
         data_out[7:0] <= data_in [7:0];  // pasar siguiente data in a siguientes 8b de data_out
         contador = 0;  // contador en 0 para pasar los datos al siguiente data_out
     end
    end
    else if(valid_in == 0)begin  // si valid_in está en 0 no se pasan datos a data_out
        valid_out <= valid_in;
        data_out <= 32'bXXXXXXXX;
        contador = 0;  // se resetea contador
    end
end
    
endmodule

phy_rx/serial_paralelo.v
module serial_paralelo
(
	input clk_4f,
	input clk_32f,
    input reset,
	input data_in,
	output reg active, //activa cuando BC counter = 4
	output reg valid_out, //activo BC_counter>4 y data2send != 0xBC
	output reg [7:0] data_out
);
integer BC_counter;		//contador de BCs
reg [7:0] data2send;		//guardo mensaje de interés y solo leo en caso importantes
integer counter;		//Contador de 0 a 7 para ir sacando valores
reg [7:0] data2send2;


	always @(posedge clk_32f) begin
		if (reset==1)begin			//Inicializa
			data_out [7:0]<= 8'b00000000;
			valid_out <= 0;
			active <= 0;
			BC_counter <= 0;
			counter <= 0;
			data2send <= 0;
		end
		else if (reset==0) begin
			data2send <= {data2send[6:0], data_in};
			
			if (BC_counter == 4 && counter == 1) 
			begin		//Si BC counter en 4, saca los datos cuando contador llega a 0
				active <= 1;
				if (data2send == 8'hBC && data2send2 != 8'hBC) 
				begin 
					valid_out <= 0;
				end
				else if (data2send != 8'hBC) begin
					data_out <= data2send;
					valid_out <= 1;
				end
			end


			else if (data2send == 8'hBC && BC_counter < 4) 
			begin
				BC_counter <= BC_counter+1;
				valid_out <= 0;
				data_out <= 0;
			end

			else if (data2send != 8'hBC && BC_counter < 4) 
			begin
				active <=0;
				valid_out <= 0;
				data_out <= 0;
			end

			if (counter == 7) begin
				counter <= 0;
			end
			else counter <= counter+1;					// va de 0-7 en un ciclo de 4f
			
			if (counter == 1) data2send2 <= data2send;
		end
	end







/*
reg [7:0] data2send;
reg [3:0] BC_counter; 
reg [3:0] selector1;



    always @(posedge clk_32f) 
    begin
		if (reset==0)
        begin	//importante para sincronizar
			data_out [7:0]<= 8'b00000000;
			valid_out <= 0;
			active <= 0;
			BC_counter <= 4'b0000;
			//counter <= 0;
			data2send <= 8'b00000000;
			//selector1 <= 4'b0000;
		end
        else
        begin
			data2send <= {data2send[6:0], data_in};
			

			if(data2send==8'hBC && BC_counter < 4'b0100)
			begin
				BC_counter <= BC_counter + 1;
				active <= 0;
				valid_out <= 0;
				data_out <= 8'h00;
			end

			else if(data2send==8'hBC && BC_counter >= 4'b0100)
			begin
				active <= 1;
				valid_out <= 0;
				data_out <= 8'h00;
			end
			else if(data2send!=8'hBC && BC_counter >= 4'b0100)
			begin
				active <= 1;
				valid_out <= 1;
				data_out <= data2send;
			end
        end
    end*/
endmodule

phy_rx/phy_rx.v
`include "un_striping.v"
`include "serial_paralelo.v" 
`include "ochoBit_32Bit.v"

module phy_rx(
    input serial_o0,
    input serial_o1,
    input  reset,
	input  clk, 
    input  clk2,
    input  clk4,
    input  clk32,
    output [31:0] output_bus);

wire [31:0] lane_0_rx, lane_1_rx;
wire  [7:0] paralelo0, paralelo1;  	// salida de serial paralelo
wire valid_0, valid_1;				// para pasar bits de valid a unstripping
wire validS_0, validS_1;			// Para bits de serial a 8-32

serial_paralelo serial_paraleloINST0(/*AUTOINST*/
				    // Outputs
				    //.active		(active),
				    .valid_out		(validS_0),
				    .data_out		(paralelo0[7:0]),
				    // Inputs
				    .clk_4f		(clk4),
				    .clk_32f		(clk32),
				    .reset		(reset),
				    .data_in		(serial_o0));
serial_paralelo serial_paraleloINST1(/*AUTOINST*/
				     // Outputs
				     //.active		(active),
				     .valid_out		(validS_1),
				     .data_out		(paralelo1[7:0]),
				     // Inputs
				     .clk_4f		(clk4),
				     .clk_32f		(clk32),
				     .reset		(reset),
				     .data_in		(serial_o1));

ochoBit_32Bit ochoBit_32BitINST0(/*AUTOINST*/
				 // Outputs
				 .valid_out		(valid_0),
				 .data_out		(lane_0_rx[31:0]),
				 // Inputs
				 .clk_4f		(clk4),
				 .clk_f			(clk),
				 .data_in		(paralelo0[7:0]),
				 .valid_in		(validS_0));

ochoBit_32Bit ochoBit_32BitINST1(/*AUTOINST*/
				 // Outputs
				 .valid_out		(valid_1),
				 .data_out		(lane_1_rx[31:0]),
				 // Inputs
				 .clk_4f		(clk4),
				 .clk_f			(clk),
				 .data_in		(paralelo1[7:0]),
				 .valid_in		(validS_1));

un_striping un_stripingINST(/*AUTOINST*/
			    // Outputs
			    .data_out		(output_bus[31:0]),
			    //.valid_out		(valid_out),
			    // Inputs
			    .clk_2f		(clk2),
			    .lane_0		(lane_0_rx[31:0]),
			    .lane_1		(lane_1_rx[31:0]),
			    .valid_0		(valid_0),
			    .valid_1		(valid_1),
			    .reset		(reset));


endmodule

phy_rx/testbench.v
`timescale 1ns/1ns

`include "phy_rx.v" 
`include "phy_rx_tester.v"
`include "generador_de_relojes.v"

module testbench; 

	wire [31:0] output_bus;
	wire valid, reset, clk, clk2, clk4, clk32, serial_o0, serial_o1;

phy_rx phy_rxINST(/*AUTOINST*/
		  // Outputs
		  .output_bus		(output_bus[31:0]),
		  // Inputs
		  .serial_o0		(serial_o0),
		  .serial_o1		(serial_o1),
		  .reset		(reset),
		  .clk			(clk),
		  .clk2			(clk2),
		  .clk4			(clk4),
		  .clk32		(clk32));

phy_rx_tester phy_rx_testerINST(/*AUTOINST*/
				// Outputs
				.serial_o0	(serial_o0),
				.serial_o1	(serial_o1),
				.clk32		(clk32),
				.reset		(reset),
				// Inputs
				.output_bus	(output_bus[31:0]));

generador_de_relojes generador_de_relojesINST(/*AUTOINST*/
					      // Outputs
					      //.CLK16		(CLK16),
					      //.CLK8		(CLK8),
					      .CLK4		(clk4),
					      .CLK2		(clk2),
					      .CLK		(clk),
					      // Inputs
					      .CLK32		(clk32));


endmodule

phy_rx/phy_rx.vcd
$date
	Fri Oct 22 00:42:28 2021
$end
$version
	Icarus Verilog
$end
$timescale
	1ns
$end
$scope module testbench $end
$var wire 1 ! serial_o1 $end
$var wire 1 " serial_o0 $end
$var wire 1 # reset $end
$var wire 32 $ output_bus [31:0] $end
$var wire 1 % clk4 $end
$var wire 1 & clk32 $end
$var wire 1 ' clk2 $end
$var wire 1 ( clk $end
$scope module generador_de_relojesINST $end
$var wire 1 ) EN1 $end
$var wire 1 * EN2 $end
$var wire 1 + EN3 $end
$var wire 1 , EN4 $end
$var wire 1 - CLK8 $end
$var wire 1 % CLK4 $end
$var wire 1 & CLK32 $end
$var wire 1 ' CLK2 $end
$var wire 1 . CLK16 $end
$var wire 1 ( CLK $end
$scope module ff0 $end
$var wire 1 / T $end
$var wire 1 & CLK $end
$var reg 1 . Q $end
$upscope $end
$scope module ff1 $end
$var wire 1 ) T $end
$var wire 1 & CLK $end
$var reg 1 - Q $end
$upscope $end
$scope module ff2 $end
$var wire 1 * T $end
$var wire 1 & CLK $end
$var reg 1 % Q $end
$upscope $end
$scope module ff3 $end
$var wire 1 + T $end
$var wire 1 & CLK $end
$var reg 1 ' Q $end
$upscope $end
$scope module ff4 $end
$var wire 1 , T $end
$var wire 1 & CLK $end
$var reg 1 ( Q $end
$upscope $end
$upscope $end
$scope module phy_rxINST $end
$var wire 1 ( clk $end
$var wire 1 ' clk2 $end
$var wire 1 % clk4 $end
$var wire 1 0 valid_1 $end
$var wire 1 1 valid_0 $end
$var wire 1 2 validS_1 $end
$var wire 1 3 validS_0 $end
$var wire 1 ! serial_o1 $end
$var wire 1 " serial_o0 $end
$var wire 1 # reset $end
$var wire 8 4 paralelo1 [7:0] $end
$var wire 8 5 paralelo0 [7:0] $end
$var wire 32 6 output_bus [31:0] $end
$var wire 32 7 lane_1_rx [31:0] $end
$var wire 32 8 lane_0_rx [31:0] $end
$var wire 1 & clk32 $end
$scope module ochoBit_32BitINST0 $end
$var wire 1 % clk_4f $end
$var wire 1 ( clk_f $end
$var wire 1 3 valid_in $end
$var wire 8 9 data_in [7:0] $end
$var reg 2 : contador [1:0] $end
$var reg 32 ; data_out [31:0] $end
$var reg 1 1 valid_out $end
$upscope $end
$scope module ochoBit_32BitINST1 $end
$var wire 1 % clk_4f $end
$var wire 1 ( clk_f $end
$var wire 1 2 valid_in $end
$var wire 8 < data_in [7:0] $end
$var reg 2 = contador [1:0] $end
$var reg 32 > data_out [31:0] $end
$var reg 1 0 valid_out $end
$upscope $end
$scope module serial_paraleloINST0 $end
$var wire 1 % clk_4f $end
$var wire 1 # reset $end
$var wire 1 " data_in $end
$var wire 1 & clk_32f $end
$var reg 1 ? active $end
$var reg 8 @ data2send [7:0] $end
$var reg 8 A data2send2 [7:0] $end
$var reg 8 B data_out [7:0] $end
$var reg 1 3 valid_out $end
$var integer 32 C BC_counter [31:0] $end
$var integer 32 D counter [31:0] $end
$upscope $end
$scope module serial_paraleloINST1 $end
$var wire 1 % clk_4f $end
$var wire 1 # reset $end
$var wire 1 ! data_in $end
$var wire 1 & clk_32f $end
$var reg 1 E active $end
$var reg 8 F data2send [7:0] $end
$var reg 8 G data2send2 [7:0] $end
$var reg 8 H data_out [7:0] $end
$var reg 1 2 valid_out $end
$var integer 32 I BC_counter [31:0] $end
$var integer 32 J counter [31:0] $end
$upscope $end
$scope module un_stripingINST $end
$var wire 1 ' clk_2f $end
$var wire 32 K lane_0 [31:0] $end
$var wire 32 L lane_1 [31:0] $end
$var wire 1 1 valid_0 $end
$var wire 1 0 valid_1 $end
$var wire 1 # reset $end
$var reg 32 M data_out [31:0] $end
$var reg 1 N selector $end
$var reg 1 O valid_out $end
$upscope $end
$upscope $end
$scope module phy_rx_testerINST $end
$var wire 32 P output_bus [31:0] $end
$var reg 1 & clk32 $end
$var reg 1 # reset $end
$var reg 1 " serial_o0 $end
$var reg 1 ! serial_o1 $end
$upscope $end
$upscope $end
$enddefinitions $end
#0
$dumpvars
bx P
xO
xN
bx M
bx L
bx K
bx J
bx I
bx H
bx G
bx F
xE
bx D
bx C
bx B
bx A
bx @
x?
bx >
bx =
bx <
bx ;
bx :
bx 9
bx 8
bx 7
bx 6
bx 5
bx 4
x3
x2
x1
x0
1/
0.
0-
0,
0+
0*
0)
0(
0'
0&
0%
bx $
1#
0"
0!
$end
#1
1)
b0 @
b0 D
b0 C
0?
03
b0 5
b0 9
b0 B
b0 F
b0 J
b0 I
0E
02
b0 4
b0 <
b0 H
0#
1.
1&
#2
0&
#3
0)
1-
0.
1!
1"
b1 J
b1 D
1&
#4
0&
#5
1*
1)
b0 A
b10 D
b1 @
b0 G
b10 J
b1 F
0!
0"
1.
1&
#6
0&
#7
01
00
b0 :
b0 =
0*
0)
1%
0-
0.
1!
1"
b11 J
b10 F
b11 D
b10 @
1&
#8
0&
#9
1)
b100 D
b101 @
b100 J
b101 F
1.
1&
#10
0&
#11
0)
1-
0.
b101 J
b1011 F
b101 D
b1011 @
1&
#12
0&
#13
1+
1*
1)
b110 D
b10111 @
b110 J
b10111 F
1.
1&
#14
0&
#15
0N
0+
0*
0)
1'
0%
0-
0.
0!
0"
b111 J
b101111 F
b111 D
b101111 @
1&
#16
0&
#17
1)
b0 D
b1011110 @
b0 J
b1011110 F
1.
1&
#18
0&
#19
0)
1-
0.
1!
1"
b1 J
b10111100 F
b1 D
b10111100 @
1&
#20
0&
#21
1*
1)
b10111100 A
b10 D
b1 C
b1111001 @
b10111100 G
b10 J
b1 I
b1111001 F
0!
0"
1.
1&
#22
0&
#23
0*
0)
1%
0-
0.
1!
1"
b11 J
b11110010 F
b11 D
b11110010 @
1&
#24
0&
#25
1)
b100 D
b11100101 @
b100 J
b11100101 F
1.
1&
#26
0&
#27
0)
1-
0.
b101 J
b11001011 F
b101 D
b11001011 @
1&
#28
0&
#29
1,
1+
1*
1)
b110 D
b10010111 @
b110 J
b10010111 F
1.
1&
#30
0&
#31
0,
0+
0*
0)
1(
0'
0%
0-
0.
0!
0"
b111 J
b101111 F
b111 D
b101111 @
1&
#32
0&
#33
1)
b0 D
b1011110 @
b0 J
b1011110 F
1.
1&
#34
0&
#35
0)
1-
0.
1!
1"
b1 J
b10111100 F
b1 D
b10111100 @
1&
#36
0&
#37
1*
1)
b10 D
b10 C
b1111001 @
b10 J
b10 I
b1111001 F
0!
0"
1.
1&
#38
0&
#39
0*
0)
1%
0-
0.
1!
1"
b11 J
b11110010 F
b11 D
b11110010 @
1&
#40
0&
#41
1)
b100 D
b11100101 @
b100 J
b11100101 F
1.
1&
#42
0&
#43
0)
1-
0.
b101 J
b11001011 F
b101 D
b11001011 @
1&
#44
0&
#45
1+
1*
1)
b110 D
b10010111 @
b110 J
b10010111 F
1.
1&
#46
0&
#47
b0 $
b0 6
b0 M
b0 P
1N
0O
0+
0*
0)
1'
0%
0-
0.
0!
0"
b111 J
b101111 F
b111 D
b101111 @
1&
#48
0&
#49
1)
b0 D
b1011110 @
b0 J
b1011110 F
1.
1&
#50
0&
#51
0)
1-
0.
1!
1"
b1 J
b10111100 F
b1 D
b10111100 @
1&
#52
0&
#53
1*
1)
b10 D
b11 C
b1111001 @
b10 J
b11 I
b1111001 F
0!
0"
1.
1&
#54
0&
#55
0*
0)
1%
0-
0.
1!
1"
b11 J
b11110010 F
b11 D
b11110010 @
1&
#56
0&
#57
1)
b100 D
b11100101 @
b100 J
b11100101 F
1.
1&
#58
0&
#59
0)
1-
0.
b101 J
b11001011 F
b101 D
b11001011 @
1&
#60
0&
#61
1,
1+
1*
1)
b110 D
b10010111 @
b110 J
b10010111 F
1.
1&
#62
0&
#63
0,
0+
0*
0)
0(
0'
0%
0-
0.
0!
0"
b111 J
b101111 F
b111 D
b101111 @
1&
#64
0&
#65
1)
b0 D
b1011110 @
b0 J
b1011110 F
1.
1&
#66
0&
#67
0)
1-
0.
1!
1"
b1 J
b10111100 F
b1 D
b10111100 @
1&
#68
0&
#69
1*
1)
b10 D
b100 C
b1111001 @
b10 J
b100 I
b1111001 F
1.
1&
#70
0&
#71
0*
0)
1%
0-
0.
b11 J
b11110011 F
b11 D
b11110011 @
1&
#72
0&
#73
1)
b100 D
b11100111 @
b100 J
b11100111 F
1.
1&
#74
0&
#75
0)
1-
0.
b101 J
b11001111 F
b101 D
b11001111 @
1&
#76
0&
#77
1+
1*
1)
b110 D
b10011111 @
b110 J
b10011111 F
1.
1&
#78
0&
#79
0N
0+
0*
0)
1'
0%
0-
0.
b111 J
b111111 F
b111 D
b111111 @
1&
#80
0&
#81
1)
b0 D
b1111111 @
b0 J
b1111111 F
1.
1&
#82
0&
#83
0)
1-
0.
b1 J
b11111111 F
b1 D
b11111111 @
1&
#84
0&
#85
1*
1)
b11111111 A
b10 D
13
b11111111 5
b11111111 9
b11111111 B
1?
b11111111 G
b10 J
12
b11111111 4
b11111111 <
b11111111 H
1E
1.
1&
#86
0&
#87
b11111111xxxxxxxxxxxxxxxxxxxxxxxx 7
b11111111xxxxxxxxxxxxxxxxxxxxxxxx >
b11111111xxxxxxxxxxxxxxxxxxxxxxxx L
10
b11111111xxxxxxxxxxxxxxxxxxxxxxxx 8
b11111111xxxxxxxxxxxxxxxxxxxxxxxx ;
b11111111xxxxxxxxxxxxxxxxxxxxxxxx K
11
b1 =
b1 :
0*
0)
1%
0-
0.
b11 J
b11 D
1&
#88
0&
#89
1)
b100 D
b100 J
0!
0"
1.
1&
#90
0&
#91
0)
1-
0.
1!
1"
b101 J
b11111110 F
b101 D
b11111110 @
1&
#92
0&
#93
1,
1+
1*
1)
b110 D
b11111101 @
b110 J
b11111101 F
1.
1&
#94
0&
#95
0,
0+
0*
0)
1(
0'
0%
0-
0.
b111 J
b11111011 F
b111 D
b11111011 @
1&
#96
0&
#97
1)
b0 D
b11110111 @
b0 J
b11110111 F
0!
0"
1.
1&
#98
0&
#99
0)
1-
0.
1!
1"
b1 J
b11101110 F
b1 D
b11101110 @
1&
#100
0&
#101
1*
1)
b11101110 A
b10 D
b11101110 5
b11101110 9
b11101110 B
b11011101 @
b11101110 G
b10 J
b11101110 4
b11101110 <
b11101110 H
b11011101 F
1.
1&
#102
0&
#103
b1111111111101110xxxxxxxxxxxxxxxx 8
b1111111111101110xxxxxxxxxxxxxxxx ;
b1111111111101110xxxxxxxxxxxxxxxx K
b1111111111101110xxxxxxxxxxxxxxxx 7
b1111111111101110xxxxxxxxxxxxxxxx >
b1111111111101110xxxxxxxxxxxxxxxx L
b10 :
b10 =
0*
0)
1%
0-
0.
b11 J
b10111011 F
b11 D
b10111011 @
1&
#104
0&
#105
1)
b100 D
b1110111 @
b100 J
b1110111 F
1.
1&
#106
0&
#107
0)
1-
0.
b101 J
b11101111 F
b101 D
b11101111 @
1&
#108
0&
#109
1+
1*
1)
b110 D
b11011111 @
b110 J
b11011111 F
1.
1&
#110
0&
#111
1O
1N
b1111111111101110xxxxxxxxxxxxxxxx $
b1111111111101110xxxxxxxxxxxxxxxx 6
b1111111111101110xxxxxxxxxxxxxxxx M
b1111111111101110xxxxxxxxxxxxxxxx P
0+
0*
0)
1'
0%
0-
0.
b111 J
b10111111 F
b111 D
b10111111 @
1&
#112
0&
#113
1)
b0 D
b1111111 @
b0 J
b1111111 F
1.
1&
#114
0&
#115
0)
1-
0.
b1 J
b11111111 F
b1 D
b11111111 @
1&
#116
0&
#117
1*
1)
b11111111 A
b10 D
b11111111 5
b11111111 9
b11111111 B
b11111111 G
b10 J
b11111111 4
b11111111 <
b11111111 H
1.
1&
#118
0&
#119
b111111111110111011111111xxxxxxxx 7
b111111111110111011111111xxxxxxxx >
b111111111110111011111111xxxxxxxx L
b111111111110111011111111xxxxxxxx 8
b111111111110111011111111xxxxxxxx ;
b111111111110111011111111xxxxxxxx K
b11 =
b11 :
0*
0)
1%
0-
0.
b11 J
b11 D
1&
#120
0&
#121
1)
b100 D
b100 J
0!
0"
1.
1&
#122
0&
#123
0)
1-
0.
1!
1"
b101 J
b11111110 F
b101 D
b11111110 @
1&
#124
0&
#125
1,
1+
1*
1)
b110 D
b11111101 @
b110 J
b11111101 F
1.
1&
#126
0&
#127
0,
0+
0*
0)
0(
0'
0%
0-
0.
b111 J
b11111011 F
b111 D
b11111011 @
1&
#128
0&
#129
1)
b0 D
b11110111 @
b0 J
b11110111 F
0!
0"
1.
1&
#130
0&
#131
0)
1-
0.
1!
1"
b1 J
b11101110 F
b1 D
b11101110 @
1&
#132
0&
#133
1*
1)
b11101110 A
b10 D
b11101110 5
b11101110 9
b11101110 B
b11011101 @
b11101110 G
b10 J
b11101110 4
b11101110 <
b11101110 H
b11011101 F
1.
1&
#134
0&
#135
b11111111111011101111111111101110 8
b11111111111011101111111111101110 ;
b11111111111011101111111111101110 K
b11111111111011101111111111101110 7
b11111111111011101111111111101110 >
b11111111111011101111111111101110 L
b0 :
b0 =
0*
0)
1%
0-
0.
b11 J
b10111011 F
b11 D
b10111011 @
1&
#136
0&
#137
1)
b100 D
b1110111 @
b100 J
b1110111 F
0!
0"
1.
1&
#138
0&
#139
0)
1-
0.
1!
1"
b101 J
b11101110 F
b101 D
b11101110 @
1&
#140
0&
#141
1+
1*
1)
b110 D
b11011101 @
b110 J
b11011101 F
1.
1&
#142
0&
#143
b11111111111011101111111111101110 $
b11111111111011101111111111101110 6
b11111111111011101111111111101110 M
b11111111111011101111111111101110 P
0N
0+
0*
0)
1'
0%
0-
0.
b111 J
b10111011 F
b111 D
b10111011 @
1&
#144
0&
#145
1)
b0 D
b1110111 @
b0 J
b1110111 F
0!
0"
1.
1&
#146
0&
#147
0)
1-
0.
1!
1"
b1 J
b11101110 F
b1 D
b11101110 @
1&
#148
0&
#149
1*
1)
b10 D
b11011101 @
b10 J
b11011101 F
0!
0"
1.
1&
#150
0&
#151
b11101110111011101111111111101110 7
b11101110111011101111111111101110 >
b11101110111011101111111111101110 L
b11101110111011101111111111101110 8
b11101110111011101111111111101110 ;
b11101110111011101111111111101110 K
b1 =
b1 :
0*
0)
1%
0-
0.
1!
1"
b11 J
b10111010 F
b11 D
b10111010 @
1&
#152
0&
#153
1)
b100 D
b1110101 @
b100 J
b1110101 F
1.
1&
#154
0&
#155
0)
1-
0.
b101 J
b11101011 F
b101 D
b11101011 @
1&
#156
0&
#157
1,
1+
1*
1)
b110 D
b11010111 @
b110 J
b11010111 F
1.
1&
#158
0&
#159
0,
0+
0*
0)
1(
0'
0%
0-
0.
0!
0"
b111 J
b10101111 F
b111 D
b10101111 @
1&
#160
0&
#161
1)
b0 D
b1011110 @
b0 J
b1011110 F
1.
1&
#162
0&
#163
0)
1-
0.
b1 J
b10111100 F
b1 D
b10111100 @
1&
#164
0&
#165
1*
1)
b10111100 A
b10 D
03
b1111000 @
b10111100 G
b10 J
02
b1111000 F
1.
1&
#166
0&
#167
bx 8
bx ;
bx K
01
bx 7
bx >
bx L
00
b0 :
b0 =
0*
0)
1%
0-
0.
b11 J
b11110000 F
b11 D
b11110000 @
1&
#168
0&
#169
1)
b100 D
b11100000 @
b100 J
b11100000 F
1.
1&
#170
0&
#171
0)
1-
0.
b101 J
b11000000 F
b101 D
b11000000 @
1&
#172
0&
