Design/Generador_de_relojes/tester.v
module tester(
    output reg CLK,
    input wire CLK2,
    input wire CLK4,
    input wire CLK8,
    input wire CLK16,
    input wire CLK32);
always #1 CLK <= ~CLK;

initial begin    
    CLK <= 0;
    end
    
initial begin
    $dumpfile("resultados.vcd");   
    $dumpvars;
    #200 $finish; 
end
endmodule

Design/Generador_de_relojes/generador_de_relojes.v
module flipflop_t(
    input wire T, CLK,
    output reg Q);
    
    initial begin    
    Q <= 1'b0;
    end
	always @(posedge CLK) begin
        if (T) begin
            Q <= ~Q;
        end  
        else begin
            Q <= Q;
        end 
    end
endmodule

module generador_de_relojes( 
    input wire CLK,
    output wire CLK2, CLK4, CLK8, CLK16, CLK32);

    wire EN1;
    wire EN2;
    wire EN3;
    wire EN4;

    and and0(EN1, CLK2, 1'b1);
    and and0(EN2, CLK4, EN1);
    and and0(EN3, CLK8, EN2);
    and and0(EN4, CLK16, EN3);

    flipflop_t ff0(.T(1'b1), .CLK(CLK), .Q(CLK2));
    flipflop_t ff1(.T(EN1), .CLK(CLK), .Q(CLK4));
    flipflop_t ff2(.T(EN2), .CLK(CLK), .Q(CLK8));
    flipflop_t ff3(.T(EN3), .CLK(CLK), .Q(CLK16));
    flipflop_t ff4(.T(EN4), .CLK(CLK), .Q(CLK32));

endmodule

Design/Generador_de_relojes/testbench.v
`timescale 1ns/1ns

`include "generador_de_relojes.v" 
`include "tester.v" 

module testbench; 

	wire CLK, CLK2, CLK4, CLK8, CLK16, CLK32; 

generador_de_relojes generador_de_relojesINST(/*AUTOINST*/
					      // Outputs
					      .CLK2		(CLK2),
					      .CLK4		(CLK4),
					      .CLK8		(CLK8),
					      .CLK16		(CLK16),
					      .CLK32		(CLK32),
					      // Inputs
					      .CLK		(CLK));

tester testerINST(/*AUTOINST*/
		  // Outputs
		  .CLK			(CLK),
		  // Inputs
		  .CLK2			(CLK2),
		  .CLK4			(CLK4),
		  .CLK8			(CLK8),
		  .CLK16		(CLK16),
		  .CLK32		(CLK32));

endmodule

Design/Generador_de_relojes/resultados.vcd
$date
	Tue Oct  5 10:34:20 2021
$end
$version
	Icarus Verilog
$end
$timescale
	1ns
$end
$scope module testbench $end
$var wire 1 ! CLK8 $end
$var wire 1 " CLK4 $end
$var wire 1 # CLK32 $end
$var wire 1 $ CLK2 $end
$var wire 1 % CLK16 $end
$var wire 1 & CLK $end
$scope module generador_de_relojesINST $end
$var wire 1 ' EN1 $end
$var wire 1 ( EN2 $end
$var wire 1 ) EN3 $end
$var wire 1 * EN4 $end
$var wire 1 ! CLK8 $end
$var wire 1 " CLK4 $end
$var wire 1 # CLK32 $end
$var wire 1 $ CLK2 $end
$var wire 1 % CLK16 $end
$var wire 1 & CLK $end
$scope module ff0 $end
$var wire 1 + T $end
$var wire 1 & CLK $end
$var reg 1 $ Q $end
$upscope $end
$scope module ff1 $end
$var wire 1 ' T $end
$var wire 1 & CLK $end
$var reg 1 " Q $end
$upscope $end
$scope module ff2 $end
$var wire 1 ( T $end
$var wire 1 & CLK $end
$var reg 1 ! Q $end
$upscope $end
$scope module ff3 $end
$var wire 1 ) T $end
$var wire 1 & CLK $end
$var reg 1 % Q $end
$upscope $end
$scope module ff4 $end
$var wire 1 * T $end
$var wire 1 & CLK $end
$var reg 1 # Q $end
$upscope $end
$upscope $end
$scope module testerINST $end
$var wire 1 % CLK16 $end
$var wire 1 $ CLK2 $end
$var wire 1 # CLK32 $end
$var wire 1 " CLK4 $end
$var wire 1 ! CLK8 $end
$var reg 1 & CLK $end
$upscope $end
$upscope $end
$enddefinitions $end
#0
$dumpvars
1+
0*
0)
0(
0'
0&
0%
0$
0#
0"
0!
$end
#1
1'
1$
1&
#2
0&
#3
0'
1"
0$
1&
#4
0&
#5
1(
1'
1$
1&
#6
0&
#7
0(
0'
1!
0"
0$
1&
#8
0&
#9
1'
1$
1&
#10
0&
#11
0'
1"
0$
1&
#12
0&
#13
1)
1(
1'
1$
1&
#14
0&
#15
0)
0(
0'
1%
0!
0"
0$
1&
#16
0&
#17
1'
1$
1&
#18
0&
#19
0'
1"
0$
1&
#20
0&
#21
1(
1'
1$
1&
#22
0&
#23
0(
0'
1!
0"
0$
1&
#24
0&
#25
1'
1$
1&
#26
0&
#27
0'
1"
0$
1&
#28
0&
#29
1*
1)
1(
1'
1$
1&
#30
0&
#31
0*
0)
0(
0'
1#
0%
0!
0"
0$
1&
#32
0&
#33
1'
1$
1&
#34
0&
#35
0'
1"
0$
1&
#36
0&
#37
1(
1'
1$
1&
#38
0&
#39
0(
0'
1!
0"
0$
1&
#40
0&
#41
1'
1$
1&
#42
0&
#43
0'
1"
0$
1&
#44
0&
#45
1)
1(
1'
1$
1&
#46
0&
#47
0)
0(
0'
1%
0!
0"
0$
1&
#48
0&
#49
1'
1$
1&
#50
0&
#51
0'
1"
0$
1&
#52
0&
#53
1(
1'
1$
1&
#54
0&
#55
0(
0'
1!
0"
0$
1&
#56
0&
#57
1'
1$
1&
#58
0&
#59
0'
1"
0$
1&
#60
0&
#61
1*
1)
1(
1'
1$
1&
#62
0&
#63
0*
0)
0(
0'
0#
0%
0!
0"
0$
1&
#64
0&
#65
1'
1$
1&
#66
0&
#67
0'
1"
0$
1&
#68
0&
#69
1(
1'
1$
1&
#70
0&
#71
0(
0'
1!
0"
0$
1&
#72
0&
#73
1'
1$
1&
#74
0&
#75
0'
1"
0$
1&
#76
0&
#77
1)
1(
1'
1$
1&
#78
0&
#79
0)
0(
0'
1%
0!
0"
0$
1&
#80
0&
#81
1'
1$
1&
#82
0&
#83
0'
1"
0$
1&
#84
0&
#85
1(
1'
1$
1&
#86
0&
#87
0(
0'
1!
0"
0$
1&
#88
0&
#89
1'
1$
1&
#90
0&
#91
0'
1"
0$
1&
#92
0&
#93
1*
1)
1(
1'
1$
1&
#94
0&
#95
0*
0)
0(
0'
1#
0%
0!
0"
0$
1&
#96
0&
#97
1'
1$
1&
#98
0&
#99
0'
1"
0$
1&
#100
0&
#101
1(
1'
1$
1&
#102
0&
#103
0(
0'
1!
0"
0$
1&
#104
0&
#105
1'
1$
1&
#106
0&
#107
0'
1"
0$
1&
#108
0&
#109
1)
1(
1'
1$
1&
#110
0&
#111
0)
0(
0'
1%
0!
0"
0$
1&
#112
0&
#113
1'
1$
1&
#114
0&
#115
0'
1"
0$
1&
#116
0&
#117
1(
1'
1$
1&
#118
0&
#119
0(
0'
1!
0"
0$
1&
#120
0&
#121
1'
1$
1&
#122
0&
#123
0'
1"
0$
1&
#124
0&
#125
1*
1)
1(
1'
1$
1&
#126
0&
#127
0*
0)
0(
0'
0#
0%
0!
0"
0$
1&
#128
0&
#129
1'
1$
1&
#130
0&
#131
0'
1"
0$
1&
#132
0&
#133
1(
1'
1$
1&
#134
0&
#135
0(
0'
1!
0"
0$
1&
#136
0&
#137
1'
1$
1&
#138
0&
#139
0'
1"
0$
1&
#140
0&
#141
1)
1(
1'
1$
1&
#142
0&
#143
0)
0(
0'
1%
0!
0"
0$
1&
#144
0&
#145
1'
1$
1&
#146
0&
#147
0'
1"
0$
1&
#148
0&
#149
1(
1'
1$
1&
#150
0&
#151
0(
0'
1!
0"
0$
1&
#152
0&
#153
1'
1$
1&
#154
0&
#155
0'
1"
0$
1&
#156
0&
#157
1*
1)
1(
1'
1$
1&
#158
0&
#159
0*
0)
0(
0'
1#
0%
0!
0"
0$
1&
#160
0&
#161
1'
1$
1&
#162
0&
#163
0'
1"
0$
1&
#164
0&
#165
1(
1'
1$
1&
#166
0&
#167
0(
0'
1!
0"
0$
1&
#168
0&
#169
1'
1$
1&
#170
0&
#171
0'
1"
0$
1&
#172
0&
#173
1)
1(
1'
1$
1&
#174
0&
#175
0)
0(
0'
1%
0!
0"
0$
1&
#176
0&
#177
1'
1$
1&
#178
0&
#179
0'
1"
0$
1&
#180
0&
#181
1(
1'
1$
1&
#182
0&
#183
0(
0'
1!
0"
0$
1&
#184
0&
#185
1'
1$
1&
#186
0&
#187
0'
1"
0$
1&
#188
0&
#189
1*
1)
1(
1'
1$
1&
#190
0&
#191
0*
0)
0(
0'
0#
0%
0!
0"
0$
1&
#192
0&
#193
1'
1$
1&
#194
0&
#195
0'
1"
0$
1&
#196
0&
#197
1(
1'
1$
1&
#198
0&
#199
0(
0'
1!
0"
0$
1&
