32b_8b/generador_relojes.v
module flipflop_t(
    input wire T, CLK,
    output reg Q);
    
    initial begin    
    Q <= 1'b0;
    end
	always @(posedge CLK) begin
        if (T) begin
            Q <= ~Q;
        end  
        else begin
            Q <= Q;
        end 
    end
endmodule

module generador_de_relojes( 
    input wire CLK,
    output wire CLK2, CLK4, CLK8, CLK16, CLK32);

    wire EN1;
    wire EN2;
    wire EN3;
    wire EN4;

    and and0(EN1, CLK2, 1'b1);
    and and0(EN2, CLK4, EN1);
    and and0(EN3, CLK8, EN2);
    and and0(EN4, CLK16, EN3);

    flipflop_t ff0(.T(1'b1), .CLK(CLK), .Q(CLK2));
    flipflop_t ff1(.T(EN1), .CLK(CLK), .Q(CLK4));
    flipflop_t ff2(.T(EN2), .CLK(CLK), .Q(CLK8));
    flipflop_t ff3(.T(EN3), .CLK(CLK), .Q(CLK16));
    flipflop_t ff4(.T(EN4), .CLK(CLK), .Q(CLK32));
    
endmodule

32b_8b/tester32b_8b.v

module tester(
    output reg clk_4f,
    input wire clk_f,
    output reg [31:0] data_in,
    output reg valid_in,
    input wire valid_out,
    input wire [7:0] data_out);

// Definición del clk 
always #5 clk_4f <= ~clk_4f; 

initial begin    
    clk_4f <= 0; valid_in <= 0;
    end
    
initial begin

    $dumpfile("resultados.vcd");   
    $dumpvars;
    
    // Lista de datos a que se le pasa a cada entrada 
    @(posedge clk_f) valid_in <= 1; data_in <= 32'hFFFBBFFF;
    @(posedge clk_f)  data_in <= 32'hDDDDDDDD;
    @(posedge clk_f) valid_in <= 0; data_in <= 32'hAAAAAAAA;
    @(posedge clk_f) valid_in <= 1; data_in <= 32'h00000003;
    @(posedge clk_f) valid_in <= 0;

    #50 $finish;
end
endmodule

32b_8b/32b_8b_estruc.v
/* Generated by Yosys 0.9 (git sha1 1979e0b) */

(* top =  1  *)
(* src = "32b_8b.v:2" *)
module conv_32b_8b_estruc(clk_4f, clk_f, data_in, valid_in, valid_out, data_out);
  (* src = "32b_8b.v:19" *)
  wire [2:0] _000_;
  (* src = "32b_8b.v:19" *)
  wire [7:0] _001_;
  (* src = "32b_8b.v:19" *)
  wire [2:0] _002_;
  (* src = "32b_8b.v:19" *)
  wire [2:0] _003_;
  (* src = "32b_8b.v:19" *)
  wire [2:0] _004_;
  (* src = "32b_8b.v:19" *)
  wire [2:0] _005_;
  (* src = "32b_8b.v:25" *)
  (* unused_bits = "3" *)
  wire [31:0] _006_;
  wire _007_;
  wire _008_;
  wire _009_;
  wire _010_;
  wire _011_;
  wire [2:0] _012_;
  wire _013_;
  wire _014_;
  wire _015_;
  wire [7:0] _016_;
  wire [7:0] _017_;
  wire [7:0] _018_;
  wire [7:0] _019_;
  (* src = "32b_8b.v:35|<techmap.v>:260|<techmap.v>:203" *)
  (* unused_bits = "2" *)
  wire [31:0] _020_;
  (* src = "32b_8b.v:2" *)
  input clk_4f;
  (* src = "32b_8b.v:3" *)
  input clk_f;
  (* src = "32b_8b.v:10" *)
  reg [2:0] contador;
  (* src = "32b_8b.v:4" *)
  input [31:0] data_in;
  (* src = "32b_8b.v:7" *)
  output [7:0] data_out;
  reg [7:0] data_out;
  (* src = "32b_8b.v:5" *)
  input valid_in;
  (* src = "32b_8b.v:6" *)
  output valid_out;
  reg valid_out;
  assign _007_ = _006_[0] |(* src = "32b_8b.v:28" *)  contador[1];
  assign _013_ = _007_ |(* src = "32b_8b.v:28" *)  contador[2];
  assign _008_ = contador[0] |(* src = "32b_8b.v:33" *)  _012_[1];
  assign _014_ = _008_ |(* src = "32b_8b.v:33" *)  contador[2];
  assign _009_ = _006_[0] |(* src = "32b_8b.v:38" *)  _012_[1];
  assign _015_ = _009_ |(* src = "32b_8b.v:38" *)  contador[2];
  assign _010_ = contador[0] |(* src = "32b_8b.v:23" *)  contador[1];
  assign _011_ = _010_ |(* src = "32b_8b.v:23" *)  contador[2];
  assign _005_[0] = _015_ ? (* src = "32b_8b.v:38" *) contador[0] : 1'h0;
  assign _005_[1] = _015_ ? (* src = "32b_8b.v:38" *) contador[1] : 1'h0;
  assign _005_[2] = _015_ ? (* src = "32b_8b.v:38" *) contador[2] : 1'h0;
  assign _004_[0] = _014_ ? (* src = "32b_8b.v:33" *) _005_[0] : _006_[0];
  assign _004_[1] = _014_ ? (* src = "32b_8b.v:33" *) _005_[1] : _006_[1];
  assign _004_[2] = _014_ ? (* src = "32b_8b.v:33" *) _005_[2] : _006_[2];
  assign _003_[0] = _013_ ? (* src = "32b_8b.v:28" *) _004_[0] : _006_[0];
  assign _003_[1] = _013_ ? (* src = "32b_8b.v:28" *) _004_[1] : _006_[1];
  assign _003_[2] = _013_ ? (* src = "32b_8b.v:28" *) _004_[2] : _006_[2];
  assign _000_[0] = valid_in ? (* src = "32b_8b.v:21" *) _002_[0] : 1'h0;
  assign _000_[1] = valid_in ? (* src = "32b_8b.v:21" *) _002_[1] : 1'h0;
  assign _000_[2] = valid_in ? (* src = "32b_8b.v:21" *) _002_[2] : 1'h0;
  assign _002_[0] = _011_ ? (* src = "32b_8b.v:23" *) _003_[0] : _006_[0];
  assign _002_[1] = _011_ ? (* src = "32b_8b.v:23" *) _003_[1] : _006_[1];
  assign _002_[2] = _011_ ? (* src = "32b_8b.v:23" *) _003_[2] : _006_[2];
  assign _017_[0] = _014_ ? (* src = "32b_8b.v:33" *) _016_[0] : data_in[8];
  assign _017_[1] = _014_ ? (* src = "32b_8b.v:33" *) _016_[1] : data_in[9];
  assign _017_[2] = _014_ ? (* src = "32b_8b.v:33" *) _016_[2] : data_in[10];
  assign _017_[3] = _014_ ? (* src = "32b_8b.v:33" *) _016_[3] : data_in[11];
  assign _017_[4] = _014_ ? (* src = "32b_8b.v:33" *) _016_[4] : data_in[12];
  assign _017_[5] = _014_ ? (* src = "32b_8b.v:33" *) _016_[5] : data_in[13];
  assign _017_[6] = _014_ ? (* src = "32b_8b.v:33" *) _016_[6] : data_in[14];
  assign _017_[7] = _014_ ? (* src = "32b_8b.v:33" *) _016_[7] : data_in[15];
  assign _016_[0] = _015_ ? (* src = "32b_8b.v:38" *) data_out[0] : data_in[0];
  assign _016_[1] = _015_ ? (* src = "32b_8b.v:38" *) data_out[1] : data_in[1];
  assign _016_[2] = _015_ ? (* src = "32b_8b.v:38" *) data_out[2] : data_in[2];
  assign _016_[3] = _015_ ? (* src = "32b_8b.v:38" *) data_out[3] : data_in[3];
  assign _016_[4] = _015_ ? (* src = "32b_8b.v:38" *) data_out[4] : data_in[4];
  assign _016_[5] = _015_ ? (* src = "32b_8b.v:38" *) data_out[5] : data_in[5];
  assign _016_[6] = _015_ ? (* src = "32b_8b.v:38" *) data_out[6] : data_in[6];
  assign _016_[7] = _015_ ? (* src = "32b_8b.v:38" *) data_out[7] : data_in[7];
  assign _018_[0] = _013_ ? (* src = "32b_8b.v:28" *) _017_[0] : data_in[16];
  assign _018_[1] = _013_ ? (* src = "32b_8b.v:28" *) _017_[1] : data_in[17];
  assign _018_[2] = _013_ ? (* src = "32b_8b.v:28" *) _017_[2] : data_in[18];
  assign _018_[3] = _013_ ? (* src = "32b_8b.v:28" *) _017_[3] : data_in[19];
  assign _018_[4] = _013_ ? (* src = "32b_8b.v:28" *) _017_[4] : data_in[20];
  assign _018_[5] = _013_ ? (* src = "32b_8b.v:28" *) _017_[5] : data_in[21];
  assign _018_[6] = _013_ ? (* src = "32b_8b.v:28" *) _017_[6] : data_in[22];
  assign _018_[7] = _013_ ? (* src = "32b_8b.v:28" *) _017_[7] : data_in[23];
  assign _019_[0] = _011_ ? (* src = "32b_8b.v:23" *) _018_[0] : data_in[24];
  assign _019_[1] = _011_ ? (* src = "32b_8b.v:23" *) _018_[1] : data_in[25];
  assign _019_[2] = _011_ ? (* src = "32b_8b.v:23" *) _018_[2] : data_in[26];
  assign _019_[3] = _011_ ? (* src = "32b_8b.v:23" *) _018_[3] : data_in[27];
  assign _019_[4] = _011_ ? (* src = "32b_8b.v:23" *) _018_[4] : data_in[28];
  assign _019_[5] = _011_ ? (* src = "32b_8b.v:23" *) _018_[5] : data_in[29];
  assign _019_[6] = _011_ ? (* src = "32b_8b.v:23" *) _018_[6] : data_in[30];
  assign _019_[7] = _011_ ? (* src = "32b_8b.v:23" *) _018_[7] : data_in[31];
  assign _001_[0] = valid_in ? (* src = "32b_8b.v:21" *) _019_[0] : 1'hx;
  assign _001_[1] = valid_in ? (* src = "32b_8b.v:21" *) _019_[1] : 1'hx;
  assign _001_[2] = valid_in ? (* src = "32b_8b.v:21" *) _019_[2] : 1'hx;
  assign _001_[3] = valid_in ? (* src = "32b_8b.v:21" *) _019_[3] : 1'hx;
  assign _001_[4] = valid_in ? (* src = "32b_8b.v:21" *) _019_[4] : 1'hx;
  assign _001_[5] = valid_in ? (* src = "32b_8b.v:21" *) _019_[5] : 1'hx;
  assign _001_[6] = valid_in ? (* src = "32b_8b.v:21" *) _019_[6] : 1'hx;
  assign _001_[7] = valid_in ? (* src = "32b_8b.v:21" *) _019_[7] : 1'hx;
  (* src = "32b_8b.v:19" *)
  always @(posedge clk_4f)
      contador[0] <= _000_[0];
  (* src = "32b_8b.v:19" *)
  always @(posedge clk_4f)
      contador[1] <= _000_[1];
  (* src = "32b_8b.v:19" *)
  always @(posedge clk_4f)
      contador[2] <= _000_[2];
  (* src = "32b_8b.v:19" *)
  always @(posedge clk_4f)
      valid_out <= valid_in;
  (* src = "32b_8b.v:19" *)
  always @(posedge clk_4f)
      data_out[0] <= _001_[0];
  (* src = "32b_8b.v:19" *)
  always @(posedge clk_4f)
      data_out[1] <= _001_[1];
  (* src = "32b_8b.v:19" *)
  always @(posedge clk_4f)
      data_out[2] <= _001_[2];
  (* src = "32b_8b.v:19" *)
  always @(posedge clk_4f)
      data_out[3] <= _001_[3];
  (* src = "32b_8b.v:19" *)
  always @(posedge clk_4f)
      data_out[4] <= _001_[4];
  (* src = "32b_8b.v:19" *)
  always @(posedge clk_4f)
      data_out[5] <= _001_[5];
  (* src = "32b_8b.v:19" *)
  always @(posedge clk_4f)
      data_out[6] <= _001_[6];
  (* src = "32b_8b.v:19" *)
  always @(posedge clk_4f)
      data_out[7] <= _001_[7];
  assign _006_[0] = contador[0] ^(* src = "32b_8b.v:38" *)  1'h1;
  assign _012_[1] = contador[1] ^(* src = "32b_8b.v:38" *)  1'h1;
  assign _006_[1] = contador[1] ^(* src = "32b_8b.v:35|<techmap.v>:263" *)  contador[0];
  assign _006_[2] = contador[2] ^(* src = "32b_8b.v:35|<techmap.v>:263" *)  _020_[1];
  assign _020_[1] = contador[1] &(* src = "32b_8b.v:35|<techmap.v>:260|<techmap.v>:221" *)  contador[0];
  assign _006_[31:4] = 28'h0000000;
  assign { _012_[2], _012_[0] } = { contador[2], contador[0] };
  assign { _020_[31:2], _020_[0] } = { 29'h00000000, _006_[3], contador[0] };
endmodule

32b_8b/32b_8b.v
module conv_32b_8b ( input wire clk_4f,
                input wire clk_f,
                input wire [31:0] data_in,
                input wire valid_in,
                output reg valid_out,
                output reg [7:0] data_out   
);

reg [2:0]contador; // Se crea un registro interno para tener un control de cuales 
                   // datos pasar a la salida

/*
initial begin
    contador = 0; 
end
*/

always @(posedge clk_4f)begin

    if (valid_in == 1)begin // Si valid_in está en 1 se empieza a pasar los datos
      valid_out <= valid_in; // Se pasa primero valid_in a valid_out
     if(contador == 0)begin
        data_out <= data_in [31:24]; // Primeros 8 bits a la salida
        contador = contador + 1; // Aumento del contador 
     end

     else if (contador == 1)begin
         data_out <= data_in [23:16]; // Segundos 8 bits a la salida
         contador = contador + 1; // Aumento del contador
     end

     else if (contador == 2)begin
         data_out <= data_in [15:8]; // Terceros 8 bits a la salida
         contador = contador + 1; // Aumento del contador
     end

     else if (contador == 3)begin
         data_out <= data_in [7:0]; // Últimos 8 bits a la salida
         contador = 0;  // Se reinicia el contador 
     end
    end
    else if(valid_in == 0)begin // Condición para cuando valid_in se encuentre en 0 
        valid_out <= valid_in; // Se pasa la señal de valid_in a valid_out
        data_out <= 8'bXXXXXXXX;  // Se pasa una señal "basura" a data_out
        contador = 0;  // Se reinicia el contador             
    end
end
    
endmodule

32b_8b/testbench32b_8b.v
`timescale 1ns/1ns

`include "32b_8b_estruc.v" 
`include "32b_8b.v" 
`include "tester32b_8b.v" 
`include "generador_relojes.v"

module testbench; 

	wire clk_f, clk_4f, valid_in, valid_out; 
    wire [31:0] data_in;
    wire [7:0] data_out, data_out_estruc ;

// Instancia utilizando modelo conductual 
conv_32b_8b convertidor1(
					      .clk_f		(clk_f),
					      .clk_4f		(clk_4f),
                          .data_in  (data_in),
                          .data_out  (data_out),
                          .valid_in  (valid_in),
                          .valid_out  (valid_out));

// Instancia utilizando modelo estructural sintetizado
conv_32b_8b_estruc convertidor2(
					      .clk_f		(clk_f),
					      .clk_4f		(clk_4f),
                          .data_in  (data_in),
                          .data_out  (data_out_estruc),
                          .valid_in  (valid_in),
                          .valid_out  (valid_out));

// Instancia para el tester 
tester tester1(
					      .clk_f		(clk_f),
					      .clk_4f		(clk_4f),
                          .data_in  (data_in),
                          .data_out  (data_out),
                          .valid_in  (valid_in),
                          .valid_out  (valid_out));

// Instancia para el generador de relojes
// Se seleccionan solamente las señales necesarias 
generador_de_relojes generador_de_relojesINST(

					      .CLK4		(clk_f),
					      .CLK		(clk_4f));
endmodule

32b_8b/resultados.vcd
$date
	Tue Oct  5 09:54:52 2021
$end
$version
	Icarus Verilog
$end
$timescale
	1ns
$end
$scope module testbench $end
$var wire 1 ! valid_out $end
$var wire 1 " valid_in $end
$var wire 8 # data_out_estruc [7:0] $end
$var wire 8 $ data_out [7:0] $end
$var wire 32 % data_in [31:0] $end
$var wire 1 & clk_f $end
$var wire 1 ' clk_4f $end
$scope module convertidor1 $end
$var wire 1 " valid_in $end
$var wire 32 ( data_in [31:0] $end
$var wire 1 & clk_f $end
$var wire 1 ' clk_4f $end
$var reg 3 ) contador [2:0] $end
$var reg 8 * data_out [7:0] $end
$var reg 1 + valid_out $end
$upscope $end
$scope module convertidor2 $end
$var wire 1 , _007_ $end
$var wire 1 - _008_ $end
$var wire 1 . _009_ $end
$var wire 1 / _010_ $end
$var wire 1 0 _011_ $end
$var wire 1 1 _013_ $end
$var wire 1 2 _014_ $end
$var wire 1 3 _015_ $end
$var wire 1 " valid_in $end
$var wire 32 4 data_in [31:0] $end
$var wire 1 & clk_f $end
$var wire 1 ' clk_4f $end
$var wire 32 5 _020_ [31:0] $end
$var wire 8 6 _019_ [7:0] $end
$var wire 8 7 _018_ [7:0] $end
$var wire 8 8 _017_ [7:0] $end
$var wire 8 9 _016_ [7:0] $end
$var wire 3 : _012_ [2:0] $end
$var wire 32 ; _006_ [31:0] $end
$var wire 3 < _005_ [2:0] $end
$var wire 3 = _004_ [2:0] $end
$var wire 3 > _003_ [2:0] $end
$var wire 3 ? _002_ [2:0] $end
$var wire 8 @ _001_ [7:0] $end
$var wire 3 A _000_ [2:0] $end
$var reg 3 B contador [2:0] $end
$var reg 8 C data_out [7:0] $end
$var reg 1 D valid_out $end
$upscope $end
$scope module generador_de_relojesINST $end
$var wire 1 E EN1 $end
$var wire 1 F EN2 $end
$var wire 1 G EN3 $end
$var wire 1 H EN4 $end
$var wire 1 I CLK8 $end
$var wire 1 & CLK4 $end
$var wire 1 J CLK32 $end
$var wire 1 K CLK2 $end
$var wire 1 L CLK16 $end
$var wire 1 ' CLK $end
$scope module ff0 $end
$var wire 1 M T $end
$var wire 1 ' CLK $end
$var reg 1 K Q $end
$upscope $end
$scope module ff1 $end
$var wire 1 E T $end
$var wire 1 ' CLK $end
$var reg 1 & Q $end
$upscope $end
$scope module ff2 $end
$var wire 1 F T $end
$var wire 1 ' CLK $end
$var reg 1 I Q $end
$upscope $end
$scope module ff3 $end
$var wire 1 G T $end
$var wire 1 ' CLK $end
$var reg 1 L Q $end
$upscope $end
$scope module ff4 $end
$var wire 1 H T $end
$var wire 1 ' CLK $end
$var reg 1 J Q $end
$upscope $end
$upscope $end
$scope module tester1 $end
$var wire 1 & clk_f $end
$var wire 8 N data_out [7:0] $end
$var wire 1 ! valid_out $end
$var reg 1 ' clk_4f $end
$var reg 32 O data_in [31:0] $end
$var reg 1 " valid_in $end
$upscope $end
$upscope $end
$enddefinitions $end
#0
$dumpvars
bx O
bx N
1M
0L
0K
0J
0I
0H
0G
0F
0E
xD
bx C
bx B
b0 A
bx @
bx ?
bx >
bx =
bx <
b0zxxx ;
bx :
bx 9
bx 8
bx 7
bx 6
b0zxx 5
bx 4
x3
x2
x1
x0
x/
x.
x-
x,
x+
bx *
bx )
bx (
0'
0&
bx %
bx $
bx #
0"
x!
$end
#5
b0 >
11
13
12
1,
1.
1-
b1 ?
b0 =
00
0/
b0z001 ;
b0z00 5
b0 <
b10 :
1E
0!
0+
b0 B
0D
1K
b0 )
1'
#10
0'
#15
b11111111 @
b11111111 6
b1 A
b11111111111110111011111111111111 %
b11111111111110111011111111111111 (
b11111111111110111011111111111111 4
b11111111111110111011111111111111 O
1"
0E
1&
0K
1'
#20
0'
#25
b11111011 @
b10 A
b10 >
b11111011 7
01
b11111011 6
b1 =
b10 ?
0,
b11111111 8
10
1/
b1 <
b0z010 ;
b11 :
b0z01 5
b11111111 9
1F
1E
b11111111 $
b11111111 *
b11111111 N
1+
b1 B
1!
1D
b11111111 #
b11111111 C
1K
b1 )
1'
#30
0'
#35
b10111111 @
b11 A
b10111111 6
b11 ?
02
b10111111 8
b10111111 7
0-
b11 =
b11 >
11
b11111011 9
1,
b10 <
b0z011 ;
b0 :
b0z00 5
0F
0E
1I
0&
0K
b11111011 #
b11111011 C
b10 B
b11111011 $
b11111011 *
b11111011 N
b10 )
1'
#40
0'
#45
b0 A
b11111111 @
b0 ?
b11111111 6
b0 >
b11111111 7
b0 =
b11111111 8
03
0.
12
1-
b0 <
b0z100 ;
b1 :
b0z11 5
b11111111 9
1E
b10111111 $
b10111111 *
b10111111 N
b11 B
b10111111 #
b10111111 C
1K
b11 )
1'
#50
0'
#55
b11011101 @
b11011101 6
b11011101110111011101110111011101 %
b11011101110111011101110111011101 (
b11011101110111011101110111011101 4
b11011101110111011101110111011101 O
b1 A
13
b0 >
b11111111 7
b0 =
b11111111 8
b1 ?
1.
11
12
00
1,
1-
0/
b0z001 ;
b10 :
b0z00 5
0E
1&
0K
b11111111 #
b11111111 C
b0 B
b11111111 $
b11111111 *
b11111111 N
b0 )
1'
#60
0'
#65
b11011101 @
b10 A
b10 >
b11011101 7
01
b11011101 6
b1 =
b10 ?
0,
b11011101 8
10
1G
1/
b1 <
b0z010 ;
b11 :
b0z01 5
b11011101 9
1F
1E
b11011101 $
b11011101 *
b11011101 N
b1 B
b11011101 #
b11011101 C
1K
b1 )
1'
#70
0'
#75
b11 A
b11 ?
02
0-
b11 =
b11 >
11
1,
b10 <
b0z011 ;
b0 :
b0z00 5
0G
0F
0E
1L
0I
0&
0K
b10 B
b10 )
1'
#80
0'
#85
b0 A
b0 ?
b0 >
b0 =
03
0.
12
1-
b0 <
b0z100 ;
b1 :
b0z11 5
1E
b11 B
1K
b11 )
1'
#90
0'
#95
b10101010 6
bx @
b10101010101010101010101010101010 %
b10101010101010101010101010101010 (
b10101010101010101010101010101010 4
b10101010101010101010101010101010 O
0"
b0 A
13
b0 >
b0 =
b1 ?
1.
11
12
00
1,
1-
0/
b0z001 ;
b10 :
b0z00 5
0E
1&
0K
b0 B
b0 )
1'
#100
0'
#105
bx 7
bx 8
bx 9
1F
1E
bx $
bx *
bx N
0+
0!
0D
bx #
bx C
1K
1'
#110
0'
#115
0F
0E
1I
0&
0K
1'
#120
0'
#125
1E
1K
1'
#130
0'
#135
b0 6
b0 @
b1 A
b11 %
b11 (
b11 4
b11 O
1"
0E
1&
0K
1'
#140
0'
#145
b0 @
b10 A
b10 >
b0 7
01
b0 6
b1 =
b10 ?
0,
b0 8
1H
10
1G
1/
b1 <
b0z010 ;
b11 :
b0z01 5
b0 9
1F
1E
b0 $
b0 *
b0 N
1+
b1 B
1!
1D
b0 #
b0 C
1K
b1 )
1'
#150
0'
#155
b11 A
b11 ?
02
0-
b11 =
b11 >
11
1,
b10 <
b0z011 ;
b0 :
b0z00 5
0H
0G
0F
0E
1J
0L
0I
0&
0K
b10 B
b10 )
1'
#160
0'
#165
b0 A
b11 @
b0 ?
b11 6
b0 >
b11 7
b0 =
b11 8
b11 9
03
0.
12
1-
b0 <
b0z100 ;
b1 :
b0z11 5
1E
b11 B
1K
b11 )
1'
#170
0'
#175
0"
b0 A
bx @
13
b0 >
b11 7
b0 =
b11 8
b1 ?
b0 6
1.
11
12
00
1,
1-
0/
b0z001 ;
b10 :
b0z00 5
0E
1&
0K
b11 #
b11 C
b0 B
b11 $
b11 *
b11 N
b0 )
1'
#180
0'
#185
bx 7
bx 8
bx 9
1F
1E
bx $
bx *
bx N
0+
0!
0D
bx #
bx C
1K
1'
#190
0'
#195
0F
0E
1I
0&
0K
1'
#200
0'
#205
1E
1K
1'
#210
0'
#215
0E
1&
0K
1'
#220
0'
#225
1G
1F
1E
1K
1'
